telegrambotmanager_andreconjo/__init__.py
telegrambotmanager_andreconjo/bot.py
telegrambotmanager_andreconjo/config.py
telegrambotmanager_andreconjo/manager_bot.py
telegrambotmanager_andreconjo-0.0.2.dist-info/LICENSE
telegrambotmanager_andreconjo-0.0.2.dist-info/METADATA
telegrambotmanager_andreconjo-0.0.2.dist-info/WHEEL
telegrambotmanager_andreconjo-0.0.2.dist-info/top_level.txt
telegrambotmanager_andreconjo-0.0.2.dist-info/RECORD
