Metadata-Version: 2.1
Name: telegrambotmanager-andreconjo
Version: 0.0.2
Summary: Package for managing and moderating groups on telegram
Author-email: André Conjo <andrehconjo@gmail.com>
Classifier: Programming Language :: Python :: 3
Classifier: License :: OSI Approved :: MIT License
Classifier: Operating System :: OS Independent
Requires-Python: >=3.7
License-File: LICENSE
Requires-Dist: pyTelegramBotAPI
